perry_the_docker_agent/__init__.py
perry_the_docker_agent/config.py
perry_the_docker_agent/constants.py
perry_the_docker_agent/core.py
perry_the_docker_agent/exceptions.py
perry_the_docker_agent/main.py
perry_the_docker_agent/providers.py
perry_the_docker_agent/sceptre/config/dev/application.yaml
perry_the_docker_agent/sceptre/config/dev/config.yaml
perry_the_docker_agent/sceptre/templates/application.yaml
perry_the_docker_agent/util.py
perry_the_docker_agent-0.2.15.dist-info/LICENSE
perry_the_docker_agent-0.2.15.dist-info/METADATA
perry_the_docker_agent-0.2.15.dist-info/WHEEL
perry_the_docker_agent-0.2.15.dist-info/entry_points.txt
perry_the_docker_agent-0.2.15.dist-info/RECORD
