Metadata-Version: 2.1
Name: perry-the-docker-agent
Version: 0.2.15
Summary: Your cool remote docker agent in the cloud
Home-page: https://github.com/daverin/perry-the-docker-agent/
License: MIT
Author: Daverin
Author-email: mail@daverin.net
Requires-Python: >3.9,<=3.11.4
Classifier: License :: OSI Approved :: MIT License
Classifier: Programming Language :: Python :: 3
Classifier: Programming Language :: Python :: 3.10
Classifier: Programming Language :: Python :: 3.11
Requires-Dist: boto3 (>=1.34.27,<2.0.0)
Requires-Dist: click (>=8.1.7,<9.0.0)
Requires-Dist: colorlog (>=6.7.0,<7.0.0)
Requires-Dist: pathspec (>=0.10.1,<0.11.0)
Requires-Dist: pydantic (>=1.10.2,<2.0.0)
Requires-Dist: sceptre (==3.3.1)
Requires-Dist: typer[all] (>=0.9.0,<0.10.0)
